odoo/addons/stock_production_lot_expired_date/README.rst
odoo/addons/stock_production_lot_expired_date/__init__.py
odoo/addons/stock_production_lot_expired_date/__manifest__.py
odoo/addons/stock_production_lot_expired_date/i18n/es.po
odoo/addons/stock_production_lot_expired_date/i18n/it.po
odoo/addons/stock_production_lot_expired_date/i18n/stock_production_lot_expired_date.pot
odoo/addons/stock_production_lot_expired_date/models/__init__.py
odoo/addons/stock_production_lot_expired_date/models/res_config_settings.py
odoo/addons/stock_production_lot_expired_date/models/stock_lot.py
odoo/addons/stock_production_lot_expired_date/readme/CONTRIBUTORS.md
odoo/addons/stock_production_lot_expired_date/readme/DESCRIPTION.md
odoo/addons/stock_production_lot_expired_date/readme/USAGE.md
odoo/addons/stock_production_lot_expired_date/static/description/icon.png
odoo/addons/stock_production_lot_expired_date/static/description/index.html
odoo/addons/stock_production_lot_expired_date/tests/__init__.py
odoo/addons/stock_production_lot_expired_date/tests/test_stock_production_lot_expired_date.py
odoo/addons/stock_production_lot_expired_date/views/res_config_settings.xml
odoo_addon_stock_production_lot_expired_date-17.0.1.0.1.2.dist-info/METADATA
odoo_addon_stock_production_lot_expired_date-17.0.1.0.1.2.dist-info/WHEEL
odoo_addon_stock_production_lot_expired_date-17.0.1.0.1.2.dist-info/top_level.txt
odoo_addon_stock_production_lot_expired_date-17.0.1.0.1.2.dist-info/RECORD
