Metadata-Version: 2.1
Name: odoo-addon-stock_production_lot_expired_date
Version: 17.0.1.0.1.2
Requires-Python: >=3.10
Requires-Dist: odoo>=17.0a,<17.1dev
Summary: Stock production lot expired date
Home-page: https://github.com/OCA/product-attribute
License: AGPL-3
Author: Camptocamp, ACSONE SA/NV, Odoo Community Association (OCA)
Author-email: support@odoo-community.org
Classifier: Programming Language :: Python
Classifier: Framework :: Odoo
Classifier: Framework :: Odoo :: 17.0
Classifier: License :: OSI Approved :: GNU Affero General Public License v3
